orderherosales/__init__.py
orderherosales/routing.py
orderherosales/tmap_inerface.py
orderherosales-0.2.1.dist-info/LICENSE
orderherosales-0.2.1.dist-info/METADATA
orderherosales-0.2.1.dist-info/WHEEL
orderherosales-0.2.1.dist-info/top_level.txt
orderherosales-0.2.1.dist-info/RECORD
