Metadata-Version: 2.1
Name: orderherosales
Version: 0.2.1
Summary: Routing solver for Orderhero sales
Home-page: https://github.com/hyeonahkimm/orderhero_sales
Author: Hyeonah Kim
Author-email: hyeonah_kim@kaist.ac.kr
Keywords: routing,solver,heuristics
License-File: LICENSE
Requires-Dist: numpy
Requires-Dist: ortools
Requires-Dist: pandas
Requires-Dist: requests
